SerialManager/CSVFile.py
SerialManager/Config.py
SerialManager/ConfigGen.py
SerialManager/ConsoleButtons.py
SerialManager/CreateConfigGUI.py
SerialManager/CustomGUI.py
SerialManager/Device.py
SerialManager/GUI_setup.py
SerialManager/YaMLFile.py
SerialManager/__init__.py
SerialManager/abeeway-config-template.yaml
SerialManager/abeeway_smartbadge_dict.py
SerialManager/main.py
SerialManager/serialmgr.py
SerialManager/smartbadgecfgdict.py
SerialManager-1.9.6.dist-info/LICENSE
SerialManager-1.9.6.dist-info/METADATA
SerialManager-1.9.6.dist-info/WHEEL
SerialManager-1.9.6.dist-info/entry_points.txt
SerialManager-1.9.6.dist-info/top_level.txt
SerialManager-1.9.6.dist-info/RECORD
