Metadata-Version: 2.1
Name: SerialManager
Version: 1.9.6
Summary: Abeeway configuration tool
Home-page: https://github.com/jlabbude/SerialManager
Author: João Lucas
Classifier: Development Status :: 3 - Alpha
Classifier: Programming Language :: Python :: 3
Requires-Python: >=3.0
License-File: LICENSE
Requires-Dist: pyserial
Requires-Dist: tk
Requires-Dist: requests
Requires-Dist: typing-extensions
Requires-Dist: kapak
Requires-Dist: pyyaml
Requires-Dist: fuzzyfinder
